byted_overpass_iescontent_pms_api/__init__.py
byted_overpass_iescontent_pms_api-0.0.1.dist-info/METADATA
byted_overpass_iescontent_pms_api-0.0.1.dist-info/WHEEL
byted_overpass_iescontent_pms_api-0.0.1.dist-info/top_level.txt
byted_overpass_iescontent_pms_api-0.0.1.dist-info/RECORD
